jm_pypi_test/__init__.py
jm_pypi_test/test.py
jm_pypi_test-0.1.dist-info/METADATA
jm_pypi_test-0.1.dist-info/WHEEL
jm_pypi_test-0.1.dist-info/top_level.txt
jm_pypi_test-0.1.dist-info/RECORD
