Metadata-Version: 2.1
Name: jm-pypi-test
Version: 0.1
Summary: for explain about pypi deploy
Home-page: UNKNOWN
Author: jm_ss.oh
Author-email: jm_ss.oh@samsung.com
License: UNKNOWN
Platform: UNKNOWN
